Metadata-Version: 2.1
Name: longplayer
Version: 0.2.0
Summary: Longplayer, a thousand-year long musical composition, implemented in Python
Home-page: https://github.com/TheLongplayerTrust/longplayer-python
Author: Daniel Jones and Jem Finer
Author-email: dan-code@erase.net
Keywords: sound,music,time,soundart
Classifier: Topic :: Multimedia :: Sound/Audio
Classifier: Topic :: Artistic Software
Classifier: Topic :: Communications
Classifier: Development Status :: 4 - Beta
Classifier: Intended Audience :: End Users/Desktop
Requires-Dist: soundfile
Requires-Dist: sounddevice
Requires-Dist: samplerate
Requires-Dist: numpy
Requires-Dist: blockbuffer
Requires-Dist: requests
